hilgeodev/__init__.py
hilgeodev/common.py
hilgeodev/hilgeodev.py
hilgeodev-0.0.1.dist-info/LICENSE
hilgeodev-0.0.1.dist-info/METADATA
hilgeodev-0.0.1.dist-info/WHEEL
hilgeodev-0.0.1.dist-info/entry_points.txt
hilgeodev-0.0.1.dist-info/top_level.txt
hilgeodev-0.0.1.dist-info/RECORD
