Metadata-Version: 2.2
Name: hilgeodev
Version: 0.0.1
Summary: A python package for geospatial processes.
Author-email: hcd <hilmican_deliktas@hotmail.com>
License: MIT License
Project-URL: Homepage, https://github.com/hcand/hilgeodev
Keywords: hilgeodev
Classifier: Intended Audience :: Developers
Classifier: License :: OSI Approved :: MIT License
Classifier: Natural Language :: English
Classifier: Programming Language :: Python :: 3.8
Classifier: Programming Language :: Python :: 3.9
Classifier: Programming Language :: Python :: 3.10
Classifier: Programming Language :: Python :: 3.11
Classifier: Programming Language :: Python :: 3.12
Requires-Python: >=3.8
License-File: LICENSE
Requires-Dist: numpy
Provides-Extra: all
Requires-Dist: hilgeodev[extra]; extra == "all"
Provides-Extra: extra
Requires-Dist: pandas; extra == "extra"
